gaussian_wrangler/__init__.py
gaussian_wrangler/_version.py
gaussian_wrangler/check_gauss.py
gaussian_wrangler/gauss_fragment.py
gaussian_wrangler/gausscom2com.py
gaussian_wrangler/gausscom2pdb.py
gaussian_wrangler/gausslog2com.py
gaussian_wrangler/gausslog2pdb.py
gaussian_wrangler/gausslog_unique.py
gaussian_wrangler/goodvibes_functions.py
gaussian_wrangler/goodvibes_helper.py
gaussian_wrangler/goodvibes_hm.py
gaussian_wrangler/gw_common.py
gaussian_wrangler/pdbs2gausscoms.py
gaussian_wrangler/plot_steps.py
gaussian_wrangler/run_gauss.py
gaussian_wrangler/smi2gausscom.py
gaussian_wrangler/vib_scale_factors.py
gaussian_wrangler/hartree/hartree-antlr-1.2.6-jar-with-dependencies.jar
gaussian_wrangler-0.5.2.2.dist-info/LICENSE
gaussian_wrangler-0.5.2.2.dist-info/METADATA
gaussian_wrangler-0.5.2.2.dist-info/WHEEL
gaussian_wrangler-0.5.2.2.dist-info/entry_points.txt
gaussian_wrangler-0.5.2.2.dist-info/top_level.txt
gaussian_wrangler-0.5.2.2.dist-info/RECORD
