Metadata-Version: 2.1
Name: gaussian-wrangler
Version: 0.5.2.2
Summary: UNKNOWN
Home-page: UNKNOWN
Author: Heather B Mayes
Author-email: hmayes@hmayes.com
License: MIT
Platform: Linux
Platform: Mac OS-X
Platform: Unix
Platform: Windows
Requires-Python: >=3.0
Requires-Dist: numpy
Requires-Dist: matplotlib
Requires-Dist: scipy
Requires-Dist: common-wrangler (>=0.3.7.2)
Requires-Dist: jpype1
Requires-Dist: pubchempy
